neured/__init__.py
neured/demo_notebooks/NeuRED_Notebook_Demo_3Dfilter.ipynb
neured/demo_notebooks/NeuRED_Notebook_Demo_withSBKG.ipynb
neured/demo_notebooks/Proc_dataflow_3Dfilter.jpg
neured/demo_notebooks/Proc_dataflow_withSBKG.jpg
neured/framework/dyn_params.py
neured/framework/file_utils.py
neured/framework/img_utils.py
neured/framework/magic_selectors.py
neured/framework/mergers.py
neured/framework/parameters.py
neured/framework/processors.py
neured/manual/NeuRED_manual_v1.docx
neured/proc_functions/align.py
neured/proc_functions/base_proc.py
neured/proc_functions/filters.py
neured/proc_functions/positionning.py
neured/proc_functions/resolution.py
neured/proc_functions/sbkg.py
neured/utilities/msel_utilities/custom.js
neured/utilities/msel_utilities/msel_utilities.js
neured/utilities/msel_utilities/readme.txt
neured-1.0.dist-info/licenses/LICENSE.txt
neured-1.0.dist-info/METADATA
neured-1.0.dist-info/WHEEL
neured-1.0.dist-info/top_level.txt
neured-1.0.dist-info/RECORD
