Metadata-Version: 2.4
Name: neured
Version: 1.0
Summary: NeuRED: Framework for Processing Time-series Neutron Radiography of Electrochemical Devices
Author-email: Jongmin Lee <jongmin.lee@psi.ch>
License-Expression: MIT
Requires-Python: >=3.10
License-File: LICENSE.txt
Requires-Dist: numpy>=1.22
Requires-Dist: scipy>=1.8
Requires-Dist: matplotlib>=3.5
Requires-Dist: opencv-python>=4.5
Requires-Dist: astropy>=5.0
Requires-Dist: jupyter>=1.0
Requires-Dist: ipython>=8.0
Requires-Dist: pyqt5>=5.15
Requires-Dist: tqdm>=4.67
Requires-Dist: h5py>=3.0
Requires-Dist: scikit-image>=0.19
Requires-Dist: pyqtgraph>=0.13
Requires-Dist: jupyter_contrib_nbextensions>=0.7
Requires-Dist: pandas>=2.2.3
Dynamic: license-file
